msfabricpysdkcore/__init__.py
msfabricpysdkcore/admin_item.py
msfabricpysdkcore/admin_workspace.py
msfabricpysdkcore/adminapi.py
msfabricpysdkcore/auth.py
msfabricpysdkcore/capacity.py
msfabricpysdkcore/client.py
msfabricpysdkcore/coreapi.py
msfabricpysdkcore/deployment_pipeline.py
msfabricpysdkcore/domain.py
msfabricpysdkcore/environment.py
msfabricpysdkcore/eventstream.py
msfabricpysdkcore/fabric_azure_capacity.py
msfabricpysdkcore/fabric_azure_client.py
msfabricpysdkcore/folder.py
msfabricpysdkcore/item.py
msfabricpysdkcore/job_instance.py
msfabricpysdkcore/lakehouse.py
msfabricpysdkcore/long_running_operation.py
msfabricpysdkcore/onelakeshortcut.py
msfabricpysdkcore/otheritems.py
msfabricpysdkcore/spark_custom_pool.py
msfabricpysdkcore/workspace.py
msfabricpysdkcore/tests/__init__.py
msfabricpysdkcore/tests/test_admin_apis.py
msfabricpysdkcore/tests/test_admin_tags.py
msfabricpysdkcore/tests/test_anomaly_detector.py
msfabricpysdkcore/tests/test_apache_airflow_job.py
msfabricpysdkcore/tests/test_connection.py
msfabricpysdkcore/tests/test_copy_jobs.py
msfabricpysdkcore/tests/test_dataflows.py
msfabricpysdkcore/tests/test_datapipelines.py
msfabricpysdkcore/tests/test_deployment_pipelinev2.py
msfabricpysdkcore/tests/test_digital_twin_builder.py
msfabricpysdkcore/tests/test_domains.py
msfabricpysdkcore/tests/test_environments.py
msfabricpysdkcore/tests/test_evenstreams.py
msfabricpysdkcore/tests/test_eventhouses.py
msfabricpysdkcore/tests/test_eventstream_topology.py
msfabricpysdkcore/tests/test_external_data_shares.py
msfabricpysdkcore/tests/test_fabric_azure_client.py
msfabricpysdkcore/tests/test_folders.py
msfabricpysdkcore/tests/test_gateways.py
msfabricpysdkcore/tests/test_git.py
msfabricpysdkcore/tests/test_graphqlapi.py
msfabricpysdkcore/tests/test_items.py
msfabricpysdkcore/tests/test_jobs.py
msfabricpysdkcore/tests/test_kql_dashboards.py
msfabricpysdkcore/tests/test_kql_queryset.py
msfabricpysdkcore/tests/test_kqldatabases.py
msfabricpysdkcore-0.2.11.dist-info/licenses/LICENSE
msfabricpysdkcore-0.2.11.dist-info/METADATA
msfabricpysdkcore-0.2.11.dist-info/WHEEL
msfabricpysdkcore-0.2.11.dist-info/top_level.txt
msfabricpysdkcore-0.2.11.dist-info/RECORD
