Metadata-Version: 2.4
Name: msfabricpysdkcore
Version: 0.2.11
Summary: A Python SDK for Microsoft Fabric
Author: Andreas Rederer
Project-URL: Homepage, https://github.com/DaSenf1860/ms-fabric-sdk-core
Classifier: Programming Language :: Python :: 3
Classifier: License :: OSI Approved :: MIT License
Classifier: Operating System :: OS Independent
Requires-Python: >=3.10
License-File: LICENSE
Requires-Dist: requests>=2.30.0
Requires-Dist: azure-identity>=1.15.0
Requires-Dist: msal>=1.28.0
Dynamic: license-file
Dynamic: requires-dist
